{
	"animations": [
		{
			"offsets": [
				0,
				0
			],
			"loop": false,
			"fps": 24,
			"anim": "idle",
			"indices": [],
			"name": "idle"
		},
		{
			"offsets": [
				280,
				0
			],
			"loop": false,
			"fps": 24,
			"anim": "singLEFT",
			"indices": [],
			"name": "left"
		},
		{
			"offsets": [
				160,
				-10
			],
			"loop": false,
			"fps": 24,
			"anim": "singDOWN",
			"indices": [],
			"name": "down"
		},
		{
			"offsets": [
				170,
				50
			],
			"loop": false,
			"fps": 24,
			"anim": "singUP",
			"indices": [],
			"name": "up"
		},
		{
			"offsets": [
				-30,
				0
			],
			"loop": false,
			"fps": 24,
			"anim": "singRIGHT",
			"indices": [],
			"name": "right"
		},
		{
			"loop": false,
			"offsets": [
				10,
				10
			],
			"anim": "idle-alt",
			"fps": 24,
			"name": "look",
			"indices": []
		}
	],
	"no_antialiasing": false,
	"image": "characters/roleplay/bernard",
	"position": [
		0,
		0
	],
	"healthicon": "retgar",
	"flip_x": false,
	"healthbar_colors": [
		105,
		197,
		255
	],
	"camera_position": [
		0,
		0
	],
	"sing_duration": 6.1,
	"scale": 1
}